setup.py
clscreen/__init__.py
clscreen/cls.py
clscreen.egg-info/PKG-INFO
clscreen.egg-info/SOURCES.txt
clscreen.egg-info/dependency_links.txt
clscreen.egg-info/entry_points.txt
clscreen.egg-info/top_level.txt