Metadata-Version: 2.1
Name: clscreen
Version: 0.0.3
Summary: Just clear the screen for goodness sake.
Home-page: UNKNOWN
Author: Flyin Ryan
Author-email: haasrr@etsu.edu
License: UNKNOWN
Platform: UNKNOWN
Classifier: Intended Audience :: Other Audience
Classifier: Programming Language :: Python :: 3 :: Only
Requires-Python: >=3.0
